{"Utah Jazz":92.6,"Seattle SuperSonics":95.5,"Orlando Magic":95.1,"San Antonio Spurs":94.6,"Chicago Bulls":92.0,"Phoenix Suns":95.9,"Portland Trail Blazers":93.8,"Indiana Pacers":90.0,"Charlotte Hornets":91.2,"New York Knicks":91.2,"Houston Rockets":94.2,"Atlanta Hawks":89.8,"Denver Nuggets":91.5,"Cleveland Cavaliers":84.8,"Los Angeles Lakers":95.2,"Sacramento Kings":92.3,"Miami Heat":92.9,"Boston Celtics":94.0,"Dallas Mavericks":94.7,"New Jersey Nets":92.3,"Milwaukee Bucks":92.7,"Golden State Warriors":97.9,"Philadelphia 76ers":91.0,"Washington Bullets":94.5,"Detroit Pistons":93.2,"Los Angeles Clippers":94.3,"Minnesota Timberwolves":91.4,"League Average":92.9}